staple/__init__.py
staple/cli.py
staple/staple.py
staple-0.3.2.dist-info/AUTHORS.rst
staple-0.3.2.dist-info/LICENSE
staple-0.3.2.dist-info/METADATA
staple-0.3.2.dist-info/WHEEL
staple-0.3.2.dist-info/entry_points.txt
staple-0.3.2.dist-info/top_level.txt
staple-0.3.2.dist-info/RECORD
