Metadata-Version: 2.1
Name: staple
Version: 0.3.2
Summary: Implementation of the STAPLE segmentation algorithm
Home-page: https://github.com/fepegar/staple
Author: Fernando Perez-Garcia
Author-email: fernando.perezgarcia.17@ucl.ac.uk
License: MIT license
Keywords: staple
Platform: UNKNOWN
Classifier: Intended Audience :: Science/Research
Classifier: License :: OSI Approved :: MIT License
Classifier: Natural Language :: English
Classifier: Programming Language :: Python :: 3.6
Classifier: Programming Language :: Python :: 3.5
Classifier: Operating System :: OS Independent
Requires-Dist: Click (>=6.0)
Requires-Dist: numpy
Requires-Dist: SimpleITK (==1.2.0)
Requires-Dist: sphinx-rtd-theme
